slack_chat_migrator-0.3.1.dist-info/licenses/LICENSE
slack_migrator/__init__.py
slack_migrator/__main__.py
slack_migrator/py.typed
slack_migrator/cli/__init__.py
slack_migrator/cli/commands.py
slack_migrator/cli/report.py
slack_migrator/core/__init__.py
slack_migrator/core/config.py
slack_migrator/core/migrator.py
slack_migrator/services/__init__.py
slack_migrator/services/discovery.py
slack_migrator/services/file.py
slack_migrator/services/message.py
slack_migrator/services/message_attachments.py
slack_migrator/services/space.py
slack_migrator/services/user.py
slack_migrator/services/chat/__init__.py
slack_migrator/services/chat/chat_uploader.py
slack_migrator/services/drive/__init__.py
slack_migrator/services/drive/drive_uploader.py
slack_migrator/services/drive/folder_manager.py
slack_migrator/services/drive/shared_drive_manager.py
slack_migrator/utils/__init__.py
slack_migrator/utils/api.py
slack_migrator/utils/formatting.py
slack_migrator/utils/logging.py
slack_migrator/utils/logging.pyi
slack_migrator/utils/permissions.py
slack_migrator/utils/user_validation.py
tests/__init__.py
tests/integration/__init__.py
tests/unit/__init__.py
tests/unit/test_config.py
slack_chat_migrator-0.3.1.dist-info/METADATA
slack_chat_migrator-0.3.1.dist-info/WHEEL
slack_chat_migrator-0.3.1.dist-info/entry_points.txt
slack_chat_migrator-0.3.1.dist-info/top_level.txt
slack_chat_migrator-0.3.1.dist-info/RECORD
