Metadata-Version: 2.4
Name: slack-chat-migrator
Version: 0.3.1
Summary: Tool for migrating Slack exports to Google Chat
Home-page: https://github.com/nicklamont/slack-chat-migrator
Author: Nick Lamont
Author-email: nick@nicklamont.com
Project-URL: Bug Tracker, https://github.com/nicklamont/slack-chat-migrator/issues
Project-URL: Documentation, https://github.com/nicklamont/slack-chat-migrator
Project-URL: Source Code, https://github.com/nicklamont/slack-chat-migrator
Keywords: slack,google-chat,migration,workspace,chat,data-migration
Classifier: Development Status :: 4 - Beta
Classifier: Intended Audience :: Developers
Classifier: Intended Audience :: System Administrators
Classifier: License :: OSI Approved :: MIT License
Classifier: Programming Language :: Python :: 3
Classifier: Programming Language :: Python :: 3.9
Classifier: Programming Language :: Python :: 3.10
Classifier: Programming Language :: Python :: 3.11
Classifier: Programming Language :: Python :: 3.12
Classifier: Topic :: Communications :: Chat
Classifier: Topic :: Utilities
Requires-Python: >=3.9
License-File: LICENSE
Requires-Dist: emoji==2.14.1
Requires-Dist: requests==2.32.4
Requires-Dist: PyYAML==6.0.2
Requires-Dist: google-auth>=2.40.0
Requires-Dist: google-api-python-client==2.177.0
Requires-Dist: google-auth-httplib2>=0.2.0
Requires-Dist: google-auth-oauthlib>=1.2.0
Requires-Dist: tqdm==4.67.1
Requires-Dist: pytest==8.4.1
Requires-Dist: black==25.1.0
Requires-Dist: mypy==1.17.1
Requires-Dist: isort==6.0.1
Requires-Dist: flake8==7.3.0
Requires-Dist: types-requests>=2.32.4
Requires-Dist: types-PyYAML>=6.0.12
Requires-Dist: mkdocs==1.6.1
Requires-Dist: mkdocs-material==9.6.16
Dynamic: author
Dynamic: author-email
Dynamic: classifier
Dynamic: description
Dynamic: description-content-type
Dynamic: home-page
Dynamic: keywords
Dynamic: license-file
Dynamic: project-url
Dynamic: requires-dist
Dynamic: requires-python
Dynamic: summary
